viteezytool/__init__.py
viteezytool/__main__.py
viteezytool/app.py
viteezytool/data/__init__.py
viteezytool/data/data_loader.py
viteezytool/data/shared.py
viteezytool/processor/__init__.py
viteezytool/processor/configuration_test.py
viteezytool/processor/processors.py
viteezytool/resources/changelog.txt
viteezytool/resources/columns.csv
viteezytool/resources/config.ini
viteezytool/resources/example_paklijst.xlsx
viteezytool/resources/img/1.png
viteezytool/resources/img/17.png
viteezytool/resources/img/19.png
viteezytool/resources/img/2.png
viteezytool/resources/img/20.png
viteezytool/resources/img/21.png
viteezytool/resources/img/22.png
viteezytool/resources/img/23.png
viteezytool/resources/img/24.png
viteezytool/resources/img/3.png
viteezytool/resources/img/4.png
viteezytool/resources/img/5.png
viteezytool/resources/img/6.png
viteezytool/resources/img/8.png
viteezytool/resources/inventory.yaml
viteezytool/resources/lookup.xlsx
viteezytool/resources/word_templates/template.docx
viteezytool-1.1.0.dist-info/entry_points.txt
viteezytool-1.1.0.dist-info/WHEEL
viteezytool-1.1.0.dist-info/METADATA
viteezytool-1.1.0.dist-info/RECORD
