Metadata-Version: 2.1
Name: viteezytool
Version: 1.1.0
Summary: Custom tool for Viteezy to generate customized word documents from an excel database
Author: sander
Author-email: sander@rolisa.nl
Requires-Python: >=3.7,<4.0
Classifier: Programming Language :: Python :: 3
Classifier: Programming Language :: Python :: 3.7
Classifier: Programming Language :: Python :: 3.8
Classifier: Programming Language :: Python :: 3.9
Requires-Dist: docxtpl (>=0.9.2,<0.10.0)
Requires-Dist: pandas (>=1.0.3,<2.0.0)
Requires-Dist: pyyaml (>=5.3.1,<6.0.0)
Requires-Dist: tqdm (>=4.46.1,<5.0.0)
Requires-Dist: xlrd (>=1.2.0,<2.0.0)
